socket_client_server/__init__.py
socket_client_server/socket_client_server.py
socket_client_server-0.5.dev3.dist-info/DESCRIPTION.rst
socket_client_server-0.5.dev3.dist-info/METADATA
socket_client_server-0.5.dev3.dist-info/RECORD
socket_client_server-0.5.dev3.dist-info/WHEEL
socket_client_server-0.5.dev3.dist-info/metadata.json
socket_client_server-0.5.dev3.dist-info/top_level.txt
